[
  {
    "id": 7301,
    "word": "dissatisfy",
    "translation": "не удовлетворять; вызывать недовольство, неудовольствие; (не discontent)"
  },
  {
    "id": 7302,
    "word": "fiver",
    "translation": "пятерка"
  },
  {
    "id": 7303,
    "word": "joiner",
    "translation": "столяр; плотник (в строительстве); работать столяром (особ. в строительстве); столярничать (делать двери, оконные рамы и т. п.); (амер. разг.) член многих организаций, клубов и т. п.; (амер. разг.) человек, охотно подписывающий воззвание, обращение и т. п. (активный общественник); (не carpenter)"
  },
  {
    "id": 7304,
    "word": "sawn",
    "translation": "пиленый; распиленные"
  },
  {
    "id": 7305,
    "word": "clobber",
    "translation": "(сл.) избить, исколотить; (разг.) одежда, хлам, тряпьё, старьё, пожитки (особ. мелкие вещи), причиндалы"
  },
  {
    "id": 7306,
    "word": "kiddy",
    "translation": "малыш"
  },
  {
    "id": 7307,
    "word": "canvass",
    "translation": "обсуждать, дебатировать, дискутировать, спорить, подробно обсуждать; ходатайствовать, собирать; собирать голоса перед выборами, вербовать сторонников перед выборами; проверять действительность результатов голосования"
  },
  {
    "id": 7308,
    "word": "grotty",
    "translation": "безобразный, никуда не годный"
  },
  {
    "id": 7309,
    "word": "tuppence",
    "translation": "два пенса"
  },
  {
    "id": 7310,
    "word": "ventilate",
    "translation": "вентилировать, проветривать"
  },
  {
    "id": 7311,
    "word": "snowdrop",
    "translation": "подснежник"
  },
  {
    "id": 7312,
    "word": "stationer",
    "translation": "торговец канцелярскими принадлежностями; книгоиздатель; книготорговец"
  },
  {
    "id": 7313,
    "word": "distil",
    "translation": "дистиллировать, перегонять, гнать"
  },
  {
    "id": 7314,
    "word": "Vietnamese",
    "translation": "вьетнамский, вьетнамец, вьетнамка"
  },
  {
    "id": 7315,
    "word": "marching",
    "translation": "марш, походный, маршировка"
  },
  {
    "id": 7316,
    "word": "rosy",
    "translation": "розовый, румяный, радужный"
  },
  {
    "id": 7317,
    "word": "canned",
    "translation": "консервированный"
  },
  {
    "id": 7318,
    "word": "navigator",
    "translation": "навигатор, штурман, мореплаватель, судоводитель, навигационная система"
  },
  {
    "id": 7319,
    "word": "jogging",
    "translation": "пробежка"
  },
  {
    "id": 7320,
    "word": "embroidery",
    "translation": "вышивка, вышивание, вышивальный, вышитое изделие"
  },
  {
    "id": 7321,
    "word": "scruffy",
    "translation": "грязный, неряшливый, покрытый перхотью, чешуйками"
  },
  {
    "id": 7322,
    "word": "morbid",
    "translation": "болезненный, нездоровый, патологический, ужасный, отвратительный"
  },
  {
    "id": 7323,
    "word": "daisy",
    "translation": "маргаритка"
  },
  {
    "id": 7324,
    "word": "fungus",
    "translation": "гриб, грибок"
  },
  {
    "id": 7325,
    "word": "hinder",
    "translation": "мешать, препятствовать, затруднять, задерживать"
  },
  {
    "id": 7326,
    "word": "knack",
    "translation": "сноровка, умение"
  },
  {
    "id": 7327,
    "word": "parrot",
    "translation": "попугай"
  },
  {
    "id": 7328,
    "word": "psychiatry",
    "translation": "психиатрия"
  },
  {
    "id": 7329,
    "word": "saddle",
    "translation": "седло, седловой, седловина"
  },
  {
    "id": 7330,
    "word": "squat",
    "translation": "корточки; сидеть на корточках; припадание к земле (животных); маленький и широкий; приземистый, коренастый; самовольно селиться на чужой или государственной земле; вселяться в пустующий дом без разрешения владельца; (разг.) садиться, присесть"
  },
  {
    "id": 7331,
    "word": "broom",
    "translation": "метла, веник, ракитник"
  },
  {
    "id": 7332,
    "word": "disconnect",
    "translation": "отключать, отсоединять, разъединять, размыкать, выключать, разобщать"
  },
  {
    "id": 7333,
    "word": "anglican",
    "translation": "англиканский; английский, английского происхождения; англиканец, англиканка, лицо англиканского вероисповедания"
  },
  {
    "id": 7334,
    "word": "ghastly",
    "translation": "(эмоц.-усил.) ужасный, страшный; смертельный; призрачный; мертвенный, мертвенно-бледный; мрачный; (эмоц.-усил.) страшно, ужасно, чрезвычайно"
  },
  {
    "id": 7335,
    "word": "hurdle",
    "translation": "препятствие, барьер; (не obstacle, obstruction, impediment, barrier, hindrance, disorder, disability, disturbance, interference, intercept, interrupt, retardation)"
  },
  {
    "id": 7336,
    "word": "windmill",
    "translation": "ветряная мельница, ветряк"
  },
  {
    "id": 7337,
    "word": "hypocrite",
    "translation": "лицемер, ханжа"
  },
  {
    "id": 7338,
    "word": "loathe",
    "translation": "ненавидеть, питать отвращение; (не dislike, hate, detest, abhor)"
  },
  {
    "id": 7339,
    "word": "zoom",
    "translation": "трансфокатор, масштабировать"
  },
  {
    "id": 7340,
    "word": "blackmail",
    "translation": "шантаж, шантажировать, вымогательство"
  },
  {
    "id": 7341,
    "word": "erode",
    "translation": "разъедать, разрушать (постепенно); подрывать, портить; выветривать, размывать; (не diminish, reduce, decrease, lessen, subtract, shorten, deteriorate, reduction, degrade)"
  },
  {
    "id": 7342,
    "word": "rake",
    "translation": "грабли; разгребать, загребать; распутный человек; передний угол"
  },
  {
    "id": 7343,
    "word": "subtract",
    "translation": "вычитать; отнимать, изымать; отчуждать; лишать (права и т. п.); (не diminish, reduce, decrease, lessen, shorten, erode, deteriorate, reduction, degrade)"
  },
  {
    "id": 7344,
    "word": "succumb",
    "translation": "поддаваться, уступать"
  },
  {
    "id": 7345,
    "word": "swine",
    "translation": "свинья, сволочь"
  },
  {
    "id": 7346,
    "word": "forgo",
    "translation": "отказываться, воздерживаться от чего-л"
  },
  {
    "id": 7347,
    "word": "relay",
    "translation": "реле, передавать, ретранслятор, релейный, транслировать, ретранслировать, смена, трансляция, перекладывать"
  },
  {
    "id": 7348,
    "word": "wiggle",
    "translation": "покачивание, ерзание; личинка; волнистая линия; покачивать(ся), ерзать, извиваться, изгибаться"
  },
  {
    "id": 7349,
    "word": "dreaded",
    "translation": "страшный, ужасный"
  },
  {
    "id": 7350,
    "word": "contraception",
    "translation": "контрацепция, применение противозачаточных средств"
  },
  {
    "id": 7351,
    "word": "deceive",
    "translation": "обманывать, вводить в заблуждение; (не delude, mislead)"
  },
  {
    "id": 7352,
    "word": "flex",
    "translation": "сгибать, изгибаться, изгибать, шнур, гнутый, гнуть, перегиб; (не move, stir, shift, budge, squirm, wriggle, writhe, locomotion, movement, motion)"
  },
  {
    "id": 7353,
    "word": "lager",
    "translation": "лагер, светлое пиво"
  },
  {
    "id": 7354,
    "word": "orphan",
    "translation": "сирота, висячая строка"
  },
  {
    "id": 7355,
    "word": "pluck",
    "translation": "срывать; собирать; ощипывать; отвага; ливер; (разг.) провалить на экзамене"
  },
  {
    "id": 7356,
    "word": "rewind",
    "translation": "перемотка, перематывать, перемотка назад, обратная перемотка"
  },
  {
    "id": 7357,
    "word": "bouquet",
    "translation": "букет"
  },
  {
    "id": 7358,
    "word": "incest",
    "translation": "кровосмешение, инцест, кровосмесительство"
  },
  {
    "id": 7359,
    "word": "nudge",
    "translation": "легкий толчок локтем; слегка подталкивать локтем; побуждать, заставлять"
  },
  {
    "id": 7360,
    "word": "shred",
    "translation": "обрывок, лоскут, шинковать, лоскуток, кромсать"
  },
  {
    "id": 7361,
    "word": "vomit",
    "translation": "рвота, рвать, блевать, извергать"
  },
  {
    "id": 7362,
    "word": "coupon",
    "translation": "купон, талон"
  },
  {
    "id": 7363,
    "word": "icing",
    "translation": "глазурь, обледенение, сахарная глазурь, наледь"
  },
  {
    "id": 7364,
    "word": "phew",
    "translation": "фу!, уф!"
  },
  {
    "id": 7365,
    "word": "ransom",
    "translation": "выкуп, выкупать, искупление"
  },
  {
    "id": 7366,
    "word": "barley",
    "translation": "ячмень"
  },
  {
    "id": 7367,
    "word": "carton",
    "translation": "картон"
  },
  {
    "id": 7368,
    "word": "elm",
    "translation": "вяз, ильм"
  },
  {
    "id": 7369,
    "word": "peck",
    "translation": "клевать, клевок"
  },
  {
    "id": 7370,
    "word": "pup",
    "translation": "щенок"
  },
  {
    "id": 7371,
    "word": "ruddy",
    "translation": "румяный, ярко-красный"
  },
  {
    "id": 7372,
    "word": "sewer",
    "translation": "сточная труба, коллектор; обеспечивать канализацией; швея/швец"
  },
  {
    "id": 7373,
    "word": "uproar",
    "translation": "шум"
  },
  {
    "id": 7374,
    "word": "marshal",
    "translation": "маршал, судебный исполнитель, выстраивать"
  },
  {
    "id": 7375,
    "word": "segregate",
    "translation": "отделять, разделять, изолировать, сегрегировать, обособлять, расслаиваться, выделять, выделяться"
  },
  {
    "id": 7376,
    "word": "boar",
    "translation": "кабан, боров, хряк; хряковина (мясо хряка); (зоол.) вепрь; (не hog)"
  },
  {
    "id": 7377,
    "word": "congested",
    "translation": "скученный"
  },
  {
    "id": 7378,
    "word": "hinge",
    "translation": "петля, шарнир, шарнирный"
  },
  {
    "id": 7379,
    "word": "violet",
    "translation": "фиолетовый, фиалка, фиолетовый цвет, темно-лиловый"
  },
  {
    "id": 7380,
    "word": "waltz",
    "translation": "вальс, вальсировать"
  },
  {
    "id": 7381,
    "word": "accrue",
    "translation": "накопляться, нарастать, прирастать"
  },
  {
    "id": 7382,
    "word": "hoot",
    "translation": "ухать, улюлюкать, гудеть"
  },
  {
    "id": 7383,
    "word": "barking",
    "translation": "лающий, окорка"
  },
  {
    "id": 7384,
    "word": "mattress",
    "translation": "матрац, тюфяк"
  },
  {
    "id": 7385,
    "word": "rectangle",
    "translation": "прямоугольник"
  },
  {
    "id": 7386,
    "word": "yawn",
    "translation": "зевать, зевок, зиять, разверзаться"
  },
  {
    "id": 7387,
    "word": "crumb",
    "translation": "крошка, кроха, крошить, крупица"
  },
  {
    "id": 7388,
    "word": "robe",
    "translation": "мантия, халат, облачаться"
  },
  {
    "id": 7389,
    "word": "unravel",
    "translation": "распутывать, разгадывать"
  },
  {
    "id": 7390,
    "word": "proverbial",
    "translation": "вошедший в поговорку, общеизвестный; выразимый в пословице, свойственный пословице"
  },
  {
    "id": 7391,
    "word": "astronomical",
    "translation": "астрономический"
  },
  {
    "id": 7392,
    "word": "blossom",
    "translation": "цветок, цвести, цвет, расцветать, зацветать"
  },
  {
    "id": 7393,
    "word": "rotary",
    "translation": "поворотный, вращающийся, ротационный, вращательный, ротор, роторный, карусельный"
  },
  {
    "id": 7394,
    "word": "sorrow",
    "translation": "скорбь, печаль, горе, сожаление, грусть"
  },
  {
    "id": 7395,
    "word": "ware",
    "translation": "товары, изделия, посуда"
  },
  {
    "id": 7396,
    "word": "freakish",
    "translation": "причудливый, капризный, прихотливый"
  },
  {
    "id": 7397,
    "word": "canoe",
    "translation": "каноэ, челнок, байдарка"
  },
  {
    "id": 7398,
    "word": "courier",
    "translation": "курьер, гонец, нарочный, фельдъегерь"
  },
  {
    "id": 7399,
    "word": "nitrate",
    "translation": "нитрат, азотнокислый, нитровать, нитратный"
  },
  {
    "id": 7400,
    "word": "vigil",
    "translation": "бодрствование, вахта"
  }
]