[
  {
    "id": 11501,
    "word": "acrylic",
    "translation": "акриловый"
  },
  {
    "id": 11502,
    "word": "afresh",
    "translation": "снова, сызнова"
  },
  {
    "id": 11503,
    "word": "aggressor",
    "translation": "агрессор, нападающая сторона"
  },
  {
    "id": 11504,
    "word": "ajar",
    "translation": "приоткрытый"
  },
  {
    "id": 11505,
    "word": "alloy",
    "translation": "сплав, легировать, лигатура, сплавлять, примешивать"
  },
  {
    "id": 11506,
    "word": "anoint",
    "translation": "помазывать"
  },
  {
    "id": 11507,
    "word": "armada",
    "translation": "армада"
  },
  {
    "id": 11508,
    "word": "awning",
    "translation": "навес, тент"
  },
  {
    "id": 11509,
    "word": "backroom",
    "translation": "задняя комната; секретный отдел, секретная лаборатория; место, где происходит секретная деятельность; засекреченный, секретный; негласный, закулисный, тайный; относящийся к закулисной политической деятельности"
  },
  {
    "id": 11510,
    "word": "battleship",
    "translation": "линкор, линейный корабль"
  },
  {
    "id": 11511,
    "word": "beehive",
    "translation": "улей"
  },
  {
    "id": 11512,
    "word": "bigot",
    "translation": "фанатик"
  },
  {
    "id": 11513,
    "word": "bookie",
    "translation": "букмекер"
  },
  {
    "id": 11514,
    "word": "cackle",
    "translation": "кудахтать, кудахтанье, гоготать, гоготанье, клохтать"
  },
  {
    "id": 11515,
    "word": "chairmanship",
    "translation": "председательство, должность председателя"
  },
  {
    "id": 11516,
    "word": "dialectical",
    "translation": "диалектический"
  },
  {
    "id": 11517,
    "word": "doorman",
    "translation": "швейцар"
  },
  {
    "id": 11518,
    "word": "downwind",
    "translation": "по ветру"
  },
  {
    "id": 11519,
    "word": "dupe",
    "translation": "надувать"
  },
  {
    "id": 11520,
    "word": "forage",
    "translation": "корм, фураж, фуражировка"
  },
  {
    "id": 11521,
    "word": "forthwith",
    "translation": "тотчас, немедленно; приказ, подлежащий незамедлительному исполнению; (не promptly, urgently, instantly, immediately, instantaneously)"
  },
  {
    "id": 11522,
    "word": "furlong",
    "translation": "восьмая часть мили (~201 м)"
  },
  {
    "id": 11523,
    "word": "galvanize",
    "translation": "оцинковывать, гальванизировать"
  },
  {
    "id": 11524,
    "word": "gangrene",
    "translation": "гангрена"
  },
  {
    "id": 11525,
    "word": "haggle",
    "translation": "торговаться, спорить, пререкаться (особ. по мелочам); спор, торговля (по поводу цен или условий); кромсать, неумело резать или рубить; (не bargain, barter, negotiate, dicker, quibble, wrangle)"
  },
  {
    "id": 11526,
    "word": "hoarse",
    "translation": "хриплый, охрипший, сиплый"
  },
  {
    "id": 11527,
    "word": "hygienic",
    "translation": "гигиенический"
  },
  {
    "id": 11528,
    "word": "imp",
    "translation": "чертенок, бесенок, постреленок"
  },
  {
    "id": 11529,
    "word": "infuriate",
    "translation": "разъярять, бесить"
  },
  {
    "id": 11530,
    "word": "jangle",
    "translation": "резкий звук, нестройный звон колоколов; гул, гам, слитый шум голосов; болтовня, пустые разговоры; пререкания, спор, ссора; издавать резкие, нестройные звуки, нестройно звучать; звенеть, бряцать; болтать, праздно разговаривать; спорить, пререкаться, ссорит"
  },
  {
    "id": 11531,
    "word": "kerosene",
    "translation": "керосин, керосиновый"
  },
  {
    "id": 11532,
    "word": "keyhole",
    "translation": "замочная скважина"
  },
  {
    "id": 11533,
    "word": "laird",
    "translation": "помещик"
  },
  {
    "id": 11534,
    "word": "languish",
    "translation": "томиться, изнывать"
  },
  {
    "id": 11535,
    "word": "launder",
    "translation": "стирать, желоб"
  },
  {
    "id": 11536,
    "word": "machete",
    "translation": "мачете"
  },
  {
    "id": 11537,
    "word": "mallet",
    "translation": "молоток, киянка, колотушка, деревянный молоток"
  },
  {
    "id": 11538,
    "word": "manicure",
    "translation": "маникюр"
  },
  {
    "id": 11539,
    "word": "masonic",
    "translation": "масонский"
  },
  {
    "id": 11540,
    "word": "maul",
    "translation": "булава; тяжелая киянка, тяжелый деревянный молот; кувалда; страшной силы удар; схватка за мяч; сильно ударять, наносить сильнейший удар, бить; расщеплять, раскалывать; сильно избивать, колошматить, отколотить, покалечить; потрепывать, повреждать, наносить"
  },
  {
    "id": 11541,
    "word": "meteor",
    "translation": "метеор, метеорный"
  },
  {
    "id": 11542,
    "word": "minefield",
    "translation": "минное поле"
  },
  {
    "id": 11543,
    "word": "minstrel",
    "translation": "менестрель"
  },
  {
    "id": 11544,
    "word": "mongrel",
    "translation": "помесь"
  },
  {
    "id": 11545,
    "word": "mope",
    "translation": "дурак, глупец; вялый, апатичный, угрюмый человек; хандра; хандрить, быть в подавленном состоянии, быть ко всему безучастным"
  },
  {
    "id": 11546,
    "word": "nab",
    "translation": "арестовать"
  },
  {
    "id": 11547,
    "word": "nourish",
    "translation": "питать"
  },
  {
    "id": 11548,
    "word": "obtrusive",
    "translation": "навязчивый"
  },
  {
    "id": 11549,
    "word": "ohm",
    "translation": "ом, омический"
  },
  {
    "id": 11550,
    "word": "outcast",
    "translation": "изгой, отверженный, изгнанник, пария, изгнанный"
  },
  {
    "id": 11551,
    "word": "persevere",
    "translation": "упорно добиваться, стойко, упорно продолжать"
  },
  {
    "id": 11552,
    "word": "pied",
    "translation": "пестрый, разноцветный, носящий пеструю одежду"
  },
  {
    "id": 11553,
    "word": "pillage",
    "translation": "грабить, грабеж, мародерство"
  },
  {
    "id": 11554,
    "word": "polka",
    "translation": "полька"
  },
  {
    "id": 11555,
    "word": "pontificate",
    "translation": "понтификат"
  },
  {
    "id": 11556,
    "word": "prawn",
    "translation": "креветка; (не shrimp)"
  },
  {
    "id": 11557,
    "word": "precipice",
    "translation": "пропасть, обрыв"
  },
  {
    "id": 11558,
    "word": "predicate",
    "translation": "предикат, предикатный, сказуемое, утверждать"
  },
  {
    "id": 11559,
    "word": "psychosomatic",
    "translation": "психосоматический"
  },
  {
    "id": 11560,
    "word": "recede",
    "translation": "отступать, спадать"
  },
  {
    "id": 11561,
    "word": "resurface",
    "translation": "покрывать заново, асфальтировать заново; всплывать на поверхность, вновь появляться на поверхности"
  },
  {
    "id": 11562,
    "word": "retrain",
    "translation": "переобучать"
  },
  {
    "id": 11563,
    "word": "sapphire",
    "translation": "сапфир; тёмно-синий цвет сапфира; похожий на сапфир"
  },
  {
    "id": 11564,
    "word": "showman",
    "translation": "шоумен"
  },
  {
    "id": 11565,
    "word": "slouch",
    "translation": "сутулость"
  },
  {
    "id": 11566,
    "word": "solder",
    "translation": "припой, паять, припаивать, спаивать, запаивать, спайка, мягкий припой"
  },
  {
    "id": 11567,
    "word": "sonata",
    "translation": "соната"
  },
  {
    "id": 11568,
    "word": "spurn",
    "translation": "отвергать с презрением; презрительно относиться; наступать, топтать, растаптывать; пинать, ударять ногой; спотыкаться, запинаться; презрительный отказ, отклонение; презрительное отношение; пинок, удар ногой; спотыкание, запинка"
  },
  {
    "id": 11569,
    "word": "starling",
    "translation": "скворец"
  },
  {
    "id": 11570,
    "word": "subservient",
    "translation": "подчиненный, раболепный"
  },
  {
    "id": 11571,
    "word": "sulphate",
    "translation": "сульфат, сернокислый"
  },
  {
    "id": 11572,
    "word": "swatch",
    "translation": "образчик, коллекция образчиков; образец, экземпляр; группа, порция"
  },
  {
    "id": 11573,
    "word": "tenement",
    "translation": "арендованное имущество/земля/помещение; снимаемая квартира; сдаваемый в аренду многоквартирный дом; (поэт.) обитель; жилище; (церк.) тело, обитель души; (не leasehold, rent, lease, recruiting, hire)"
  },
  {
    "id": 11574,
    "word": "thunderbolt",
    "translation": "удар молнии; белемнит, чертов палец"
  },
  {
    "id": 11575,
    "word": "treachery",
    "translation": "предательство, измена, вероломство"
  },
  {
    "id": 11576,
    "word": "utensil",
    "translation": "посуда"
  },
  {
    "id": 11577,
    "word": "vane",
    "translation": "флюгер, лопатка, лопасть, крыло"
  },
  {
    "id": 11578,
    "word": "wafer",
    "translation": "облатка, вафля, подложка, пластинка, пластина"
  },
  {
    "id": 11579,
    "word": "waggle",
    "translation": "покачивание"
  },
  {
    "id": 11580,
    "word": "whirlpool",
    "translation": "водоворот, воронка"
  },
  {
    "id": 11581,
    "word": "writhe",
    "translation": "корчиться, извиваться; (with, at, under) остро переживать, мучиться, терзаться; скрутить, перекрутить (что-л.); переплетать; (не move, stir, shift, budge, squirm, wriggle, flex, locomotion, movement, motion)"
  },
  {
    "id": 11582,
    "word": "assay",
    "translation": "анализ, проба, пробирный анализ"
  },
  {
    "id": 11583,
    "word": "primer",
    "translation": "букварь, грунтовка, капсюль, грунт, запал"
  },
  {
    "id": 11584,
    "word": "endogenous",
    "translation": "эндогенный"
  },
  {
    "id": 11585,
    "word": "fetal",
    "translation": "эмбриональный, плодный, зародышевый"
  },
  {
    "id": 11586,
    "word": "metabolic",
    "translation": "метаболический, обменный"
  },
  {
    "id": 11587,
    "word": "subset",
    "translation": "подмножество, подгруппа, подкласс, сокращенный вариант"
  },
  {
    "id": 11588,
    "word": "antigen",
    "translation": "антиген"
  },
  {
    "id": 11589,
    "word": "apparel",
    "translation": "наряд"
  },
  {
    "id": 11590,
    "word": "efficacy",
    "translation": "эффективность, действенность, сила"
  },
  {
    "id": 11591,
    "word": "mosque",
    "translation": "мечеть"
  },
  {
    "id": 11592,
    "word": "cortex",
    "translation": "кора"
  },
  {
    "id": 11593,
    "word": "systemic",
    "translation": "системный"
  },
  {
    "id": 11594,
    "word": "firefly",
    "translation": "светляк"
  },
  {
    "id": 11595,
    "word": "homologous",
    "translation": "гомологичный, гомологический"
  },
  {
    "id": 11596,
    "word": "cardiovascular",
    "translation": "сердечно-сосудистый"
  },
  {
    "id": 11597,
    "word": "splice",
    "translation": "склейка, сращивание, соединение, сращивать, сросток, склеивать, сплесень, сплеснивать"
  },
  {
    "id": 11598,
    "word": "cv",
    "translation": "резюме"
  },
  {
    "id": 11599,
    "word": "basal",
    "translation": "основной, базальный"
  },
  {
    "id": 11600,
    "word": "bovine",
    "translation": "коровий, бычий; как корова, как бык, медлительный, глупый"
  }
]